melpoi/dataframe/__init__.py
melpoi/dataframe/analyzer.py
melpoi/dataframe/exception.py
melpoi/dataframe/metadata.py
melpoi/sql/__init__.py
melpoi/sql/analyzer.py
melpoi-0.2.1.dist-info/WHEEL
melpoi-0.2.1.dist-info/LICENSE
melpoi-0.2.1.dist-info/METADATA
melpoi-0.2.1.dist-info/RECORD
